{
  "color": {
    "white": {
      "value": "#FFFFFF",
      "type": "color"
    },
    "black": {
      "value": "#000000",
      "type": "color"
    },
    "transparent": {
      "value": "rgba(255,255,255,0)",
      "type": "color"
    },
    "bg": {
      "canvas": {
        "value": "{ref.palette.neutral.10}",
        "type": "color"
      },
      "surface": {
        "value": "{ref.palette.neutral.50}",
        "type": "color"
      },
      "muted": {
        "value": "{ref.palette.neutral.70}",
        "type": "color"
      },
      "subtle": {
        "value": "{ref.palette.neutral.60}",
        "type": "color"
      },
      "cover": {
        "value": "{ref.palette.neutral.30}",
        "type": "color"
      },
      "inverse": {
        "value": "{color.bg.surface}",
        "type": "color",
        "$extensions": {
          "studio.tokens": {
            "modify": {
              "type": "lighten",
              "value": "1",
              "space": "srgb"
            }
          }
        }
      }
    },
    "fg": {
      "default": {
        "value": "{ref.palette.neutral.95}",
        "type": "color"
      },
      "emphasis": {
        "value": "{ref.palette.neutral.99}",
        "type": "color"
      },
      "muted": {
        "value": "{ref.palette.neutral.90}",
        "type": "color"
      },
      "subtle": {
        "value": "{ref.palette.neutral.80}",
        "type": "color"
      },
      "inverse": {
        "value": "{ref.palette.neutral.10}",
        "type": "color"
      },
      "disabled": {
        "value": "{ref.palette.neutral.60}",
        "type": "color"
      },
      "on-disabled": {
        "value": "{ref.palette.neutral.50}",
        "type": "color"
      }
    },
    "accent": {
      "default": {
        "value": "{ref.palette.accent.60}",
        "type": "color"
      },
      "emphasis": {
        "value": "{ref.palette.accent.80}",
        "type": "color"
      },
      "muted": {
        "value": "{ref.palette.accent.30}",
        "type": "color"
      },
      "subtle": {
        "value": "{ref.palette.accent.20}",
        "type": "color"
      },
      "inverse": {
        "value": "{ref.palette.accent.99}",
        "type": "color"
      },
      "disabled": {
        "value": "{ref.palette.accent.30}",
        "type": "color"
      },
      "on-disabled": {
        "value": "{ref.palette.neutral.70}",
        "type": "color"
      }
    },
    "info": {
      "default": {
        "value": "{ref.palette.info.60}",
        "type": "color"
      },
      "emphasis": {
        "value": "{ref.palette.info.80}",
        "type": "color"
      },
      "muted": {
        "value": "{ref.palette.info.30}",
        "type": "color"
      },
      "subtle": {
        "value": "{ref.palette.info.20}",
        "type": "color"
      },
      "inverse": {
        "value": "{ref.palette.info.99}",
        "type": "color"
      },
      "disabled": {
        "value": "{ref.palette.info.30}",
        "type": "color"
      }
    },
    "success": {
      "default": {
        "value": "{ref.palette.success.60}",
        "type": "color"
      },
      "emphasis": {
        "value": "{ref.palette.success.80}",
        "type": "color"
      },
      "muted": {
        "value": "{ref.palette.success.30}",
        "type": "color"
      },
      "subtle": {
        "value": "{ref.palette.success.20}",
        "type": "color"
      },
      "inverse": {
        "value": "{ref.palette.success.99}",
        "type": "color"
      },
      "disabled": {
        "value": "{ref.palette.success.30}",
        "type": "color"
      }
    },
    "danger": {
      "default": {
        "value": "{ref.palette.danger.60}",
        "type": "color"
      },
      "emphasis": {
        "value": "{ref.palette.danger.80}",
        "type": "color"
      },
      "muted": {
        "value": "{ref.palette.danger.30}",
        "type": "color"
      },
      "subtle": {
        "value": "{ref.palette.danger.20}",
        "type": "color"
      },
      "inverse": {
        "value": "{ref.palette.danger.99}",
        "type": "color"
      },
      "disabled": {
        "value": "{ref.palette.danger.30}",
        "type": "color"
      }
    },
    "warning": {
      "default": {
        "value": "{ref.palette.warning.60}",
        "type": "color"
      },
      "emphasis": {
        "value": "{ref.palette.warning.80}",
        "type": "color"
      },
      "muted": {
        "value": "{ref.palette.warning.30}",
        "type": "color"
      },
      "subtle": {
        "value": "{ref.palette.warning.20}",
        "type": "color"
      },
      "inverse": {
        "value": "{ref.palette.warning.99}",
        "type": "color"
      },
      "disabled": {
        "value": "{ref.palette.warning.30}",
        "type": "color"
      }
    },
    "input": {
      "bg": {
        "default": {
          "value": "{ref.palette.neutral.30}",
          "type": "color"
        },
        "disabled": {
          "value": "{ref.palette.neutral.40}",
          "type": "color"
        }
      },
      "fg": {
        "default": {
          "value": "{ref.palette.neutral.95}",
          "type": "color"
        },
        "placeholder": {
          "value": "{ref.palette.neutral.70}",
          "type": "color"
        },
        "disabled": {
          "value": "{ref.palette.neutral.60}",
          "type": "color"
        }
      },
      "border": {
        "default": {
          "value": "{ref.palette.neutral.70}",
          "type": "color"
        },
        "disabled": {
          "value": "{ref.palette.neutral.60}",
          "type": "color"
        }
      }
    },
    "border": {
      "default": {
        "value": "{ref.palette.neutral.70}",
        "type": "color"
      },
      "subtle": {
        "value": "{ref.palette.neutral.60}",
        "type": "color"
      },
      "disabled": {
        "value": "{ref.palette.neutral.60}",
        "type": "color"
      }
    },
    "skeleton": {
      "default": {
        "value": "{ref.palette.neutral.60}",
        "type": "color",
        "description": "The default color for skeletons."
      },
      "on-subtle": {
        "value": "{ref.palette.neutral.70}",
        "type": "color",
        "description": "The default color to use for skeletons on subtle backgrounds."
      },
      "fg": {
        "value": "{ref.palette.neutral.80}",
        "type": "color",
        "description": "For Skeleton foreground elements, such as loader"
      },
      "gradient": {
        "value": "linear-gradient(90deg, rgba($color.bg.surface,0) 0%, rgba($color.bg.surface,0.5) 50%, rgba($color.bg.surface,0) 100%)",
        "type": "color",
        "description": "For the gradient that animates across skeletons"
      }
    },
    "image": {
      "bg": {
        "value": "{color.transparent}",
        "type": "color",
        "description": "The default background color applied to images."
      },
      "border": {
        "value": "{color.transparent}",
        "type": "color",
        "description": "The default border color applied to images."
      }
    },
    "icon": {
      "default": {
        "value": "{color.fg.default}",
        "type": "color",
        "description": "The default color applied to icons."
      },
      "fg": {
        "value": "{color.transparent}",
        "type": "color",
        "description": "The default foreground color applied to filled boxed icons."
      }
    }
  }
}